<?xml version="1.0" encoding="utf-8" ?>
<dwsync>
<file name="colorpicker.jpg" server="C:/xampp/htdocs/drupal/" local="129598207960000000" remote="129598207960000000" />
<file name="flash.gif" server="C:/xampp/htdocs/drupal/" local="129598207960000000" remote="129598207960000000" />
<file name="icons.gif" server="C:/xampp/htdocs/drupal/" local="129598207960000000" remote="129598207960000000" />
<file name="iframe.gif" server="C:/xampp/htdocs/drupal/" local="129598207960000000" remote="129598207960000000" />
<file name="pagebreak.gif" server="C:/xampp/htdocs/drupal/" local="129598207960000000" remote="129598207960000000" />
<file name="quicktime.gif" server="C:/xampp/htdocs/drupal/" local="129598207960000000" remote="129598207960000000" />
<file name="realmedia.gif" server="C:/xampp/htdocs/drupal/" local="129598207960000000" remote="129598207960000000" />
<file name="shockwave.gif" server="C:/xampp/htdocs/drupal/" local="129598207960000000" remote="129598207960000000" />
<file name="trans.gif" server="C:/xampp/htdocs/drupal/" local="129598207960000000" remote="129598207960000000" />
<file name="video.gif" server="C:/xampp/htdocs/drupal/" local="129598207960000000" remote="129598207960000000" />
<file name="windowsmedia.gif" server="C:/xampp/htdocs/drupal/" local="129598207960000000" remote="129598207960000000" />
</dwsync>